	{	
			"att":{
			"opid": "OEM Device ID. Factory set.",
			"ppid": "PAYG Device ID. Factory set. Field override options.",
			"flid": "Fleet ID. Factory set. Field override options.",
			"ccid": "iccid ",
			"frmv": "Firmware Version. Factory set."
			},
		 "cmd":{
			"pubk": "Public Key / Last Code",
			"gstw": "GPRS Sleep Time Window in mins",
			"gctw": "GPRS Connect Time Window in mins",
			"napn": "GPRS Carrier APN Name",
			"swch": "Generic device switch swch = ON | OFF ",
			"read": "Last read request of ANY GATT <data> = [opid|...|]",
			"rptm": "Set notification request mode = [0|1|2|3|4], 0: Auto-Periodic | 1 = Request-Response | 2 = Change-Notification",
			"raml": "raml list set",
		    "hbfq": "Heart Beat Interval Minutes" 
		},
		 "sts": {
            "sstc": "System Status Code",
            "crtm": "created at time",
            "udtm": "update at time",
            "time": "Device internal timer readout at last communication",
            "plat": "Device GPS Latitude",
            "plon": "Device GPS Longitude",
            "gpss": "GPS Signal Strength in db",
            "gpfc": "GPRS Connect Failure Counts",
            "rcrd": "Remaining Credit Days",
            "trhd": "Total Running History Days",
            "tpgd": "PAYG Running Days",
            "pgst": "PAYG State = PAYG | FREE",
            "tkre": "Last token entry response = NEW | REPEAT | ERROR",
            "ocst": "Device Output State = ENABLED | DISABLED"
        },
		 "dta":{
			"rvov": "Rated Inverter Output Voltage- Unit:V",
			"rabp": "Rated AC Bypass Output Power- Unit:W",
			"raip": "Rated AC Inverter Output Power- Unit:W",
			"raap": "Rated AC Charging Power- Unit:W",
			"ravp": "Rated PV Charging Power- Unit:W",
			"pckv": "Pack Voltage mV",
			"pckc": "Pack Current in mA",
			"rsoc": "Relative State of Charge",
			"rcap": "Remaining Capacity in Ahs",
			"fccp": "Full Charge Capacity in Ahs",
			"pvgd": "Pack Temperature in Celsius",
			"acyc": "Accumulated Cycles",
			"slon": "Satellite Longitude in DD (decimal degrees)",
			"slat": "Satellite Latitude in DD (decimal degrees)",
			"salt": "Satellite Altitude in Metres",
			"sstm": "Satellite-Synchronized Network Clock time in ISO 8601",
			"sgps": "Satellite GPS Strength",
			"sspe": "Satellite Speed in kM/h",
			"pviv": "Photovoltaic (PV) Input Voltage -Unit:V",
			"pvip": "Accumulated Energy Output in Ah",
			"acop": "AC Output Power -Unit:W",
			"acov": "AC Output Voltage -Unit:V",
			"pvcg": "Cumulative PV Power Generation-Unit:Wh",
			"acif": "AC Input Frequency -Unit:Hz",
			"acfr": "AC Output Frequency -Unit:Hz",
			"ccht": "Charging Cumulative Time -Unit:h",
			"dcht": "Discharging Cumulative Time -Unit:h" 
		},
		"dia":{
			"cv01": "Cell 01 Voltage mV",
            "cv02": "Cell 02 Voltage mV",
            "cv03": "Cell 03 Voltage mV",
            "cv04": "Cell 04 Voltage mV",
 			"pkt2": "Pack Temperature-2 Celsius",
            "pkt3": "Pack Temperature-3 Celsius",
            "pkt4": "Pack Temperature-4 Celsius",
            "pkt5": "Pack Temperature-5 Celsius",
            "pkt6": "Pack Temperature-6 Celsius" 
		}
	}